response_codes/_1xx_informational.py
response_codes/_2xx_success.py
response_codes/_3xx_redirection.py
response_codes/_4xx_client_errors.py
response_codes/_5xx_server_errors.py
response_codes/__init__.py
response_codes/_core.py
response_codes/_groups.py
response_codes/py.typed
http_response_codes-0.5.0.dist-info/WHEEL
http_response_codes-0.5.0.dist-info/METADATA
http_response_codes-0.5.0.dist-info/RECORD
