Metadata-Version: 2.3
Name: http-response-codes
Version: 0.5.0
Summary: A comprehensive Python library providing HTTP status code constants and exceptions
Keywords: http,status,codes,exceptions,response
Author: Grant Ramsay
Author-email: Grant Ramsay <seapagan@gmail.com>
License: MIT
Classifier: Development Status :: 4 - Beta
Classifier: Intended Audience :: Developers
Classifier: License :: OSI Approved :: MIT License
Classifier: Operating System :: OS Independent
Classifier: Programming Language :: Python :: 3
Classifier: Programming Language :: Python :: 3.9
Classifier: Programming Language :: Python :: 3.10
Classifier: Programming Language :: Python :: 3.11
Classifier: Programming Language :: Python :: 3.12
Classifier: Programming Language :: Python :: 3.13
Classifier: Programming Language :: Python :: 3.14
Classifier: Topic :: Internet :: WWW/HTTP
Classifier: Topic :: Software Development :: Libraries :: Python Modules
Requires-Python: >=3.9
Project-URL: Bug Tracker, https://github.com/seapagan/response-codes/issues
Project-URL: Documentation, https://github.com/seapagan/response-codes#readme
Project-URL: Homepage, https://github.com/seapagan/response-codes
Project-URL: Repository, https://github.com/seapagan/response-codes
